quick-silicon-sequence-generator-solution/seq_generator.sv
module seq_generator (
  input   logic        clk,
  input   logic        reset,

  output  logic [31:0] seq_o
);

  // Write your logic here...
  logic [31:0] d0_in, d0_out, d1_in, d1_out, d2_in, d2_out;

assign d0_in = d1_out;
assign d1_in = d2_out;
assign d2_in = d1_out + d0_out;

  always_ff @(posedge clk or posedge reset) begin
    if(reset) begin
      d0_out <= 32'd0;
      d1_out <= 32'd1;
      d2_out <= 32'd1;
    end
    else begin
      d0_out <= d0_in;
      d1_out <= d1_in;
      d2_out <= d2_in;
    end
    
  end

  assign seq_o = d0_out;

  
endmodule

quick-silicon-sequence-generator-solution/tb_seq_gen.sv
module tb_seq_gen ();

  logic clk;
  logic reset;
  logic [31:0] seq_o;

  // Instantiate the Fibonacci module
  seq_generator uut (
    .clk(clk),
    .reset(reset),
    .seq_o(seq_o)
  );
  
  initial begin
    $dumpfile("qs_seq_gen.vcd"); // Specify the VCD file for waveform output
    $dumpvars(0, tb_seq_gen); // Dump all variables in the testbench
  end


  // Clock generation
  initial begin
    clk = 1;
    forever #5 clk = ~clk; // Toggle clock every 5 time units
  end

  // Testbench stimulus
  initial begin
    reset = 0; // Assert reset
    #20;
    reset = 1;
    #10;
    reset = 0; // Deassert reset

    // Wait for a few clock cycles to observe the output
    #600;

    $finish; // End simulation
  end

  endmodule

quick-silicon-sequence-generator-solution/qs_seq_gen.vcd
$date
	Thu Jul 24 03:57:05 2025
$end
$version
	Icarus Verilog
$end
$timescale
	1s
$end
$scope module tb_seq_gen $end
$var wire 32 ! seq_o [31:0] $end
$var reg 1 " clk $end
$var reg 1 # reset $end
$scope module uut $end
$var wire 1 " clk $end
$var wire 32 $ d0_in [31:0] $end
$var wire 32 % d1_in [31:0] $end
$var wire 1 # reset $end
$var wire 32 & seq_o [31:0] $end
$var wire 32 ' d2_in [31:0] $end
$var reg 32 ( d0_out [31:0] $end
$var reg 32 ) d1_out [31:0] $end
$var reg 32 * d2_out [31:0] $end
$upscope $end
$upscope $end
$enddefinitions $end
$comment Show the parameter values. $end
$dumpall
$end
#0
$dumpvars
bx *
bx )
bx (
bx '
bx &
bx %
bx $
0#
1"
bx !
$end
#5
0"
#10
1"
#15
0"
#20
b1 %
b1 *
b1 '
b1 $
b1 )
b0 !
b0 &
b0 (
1"
1#
#25
0"
#30
b10 '
b1 !
b1 &
b1 (
1"
0#
#35
0"
#40
b10 %
b10 *
1"
#45
0"
#50
b11 '
b10 $
b10 )
1"
#55
0"
#60
b11 %
b11 *
b100 '
b10 !
b10 &
b10 (
1"
#65
0"
#70
b100 %
b100 *
b101 '
b11 $
b11 )
1"
#75
0"
#80
b101 %
b101 *
b100 $
b100 )
b111 '
b11 !
b11 &
b11 (
1"
#85
0"
#90
b111 %
b111 *
b101 $
b101 )
b1001 '
b100 !
b100 &
b100 (
1"
#95
0"
#100
b1001 %
b1001 *
b111 $
b111 )
b1100 '
b101 !
b101 &
b101 (
1"
#105
0"
#110
b1100 %
b1100 *
b1001 $
b1001 )
b10000 '
b111 !
b111 &
b111 (
1"
#115
0"
#120
b10000 %
b10000 *
b1100 $
b1100 )
b10101 '
b1001 !
b1001 &
b1001 (
1"
#125
0"
#130
b10101 %
b10101 *
b10000 $
b10000 )
b11100 '
b1100 !
b1100 &
b1100 (
1"
#135
0"
#140
b11100 %
b11100 *
b10101 $
b10101 )
b100101 '
b10000 !
b10000 &
b10000 (
1"
#145
0"
#150
b100101 %
b100101 *
b11100 $
b11100 )
b110001 '
b10101 !
b10101 &
b10101 (
1"
#155
0"
#160
b110001 %
b110001 *
b100101 $
b100101 )
b1000001 '
b11100 !
b11100 &
b11100 (
1"
#165
0"
#170
b1000001 %
b1000001 *
b110001 $
b110001 )
b1010110 '
b100101 !
b100101 &
b100101 (
1"
#175
0"
#180
b1010110 %
b1010110 *
b1000001 $
b1000001 )
b1110010 '
b110001 !
b110001 &
b110001 (
1"
#185
0"
#190
b1110010 %
b1110010 *
b1010110 $
b1010110 )
b10010111 '
b1000001 !
b1000001 &
b1000001 (
1"
#195
0"
#200
b10010111 %
b10010111 *
b1110010 $
b1110010 )
b11001000 '
b1010110 !
b1010110 &
b1010110 (
1"
#205
0"
#210
b11001000 %
b11001000 *
b10010111 $
b10010111 )
b100001001 '
b1110010 !
b1110010 &
b1110010 (
1"
#215
0"
#220
b100001001 %
b100001001 *
b11001000 $
b11001000 )
b101011111 '
b10010111 !
b10010111 &
b10010111 (
1"
#225
0"
#230
b101011111 %
b101011111 *
b100001001 $
b100001001 )
b111010001 '
b11001000 !
b11001000 &
b11001000 (
1"
#235
0"
#240
b111010001 %
b111010001 *
b101011111 $
b101011111 )
b1001101000 '
b100001001 !
b100001001 &
b100001001 (
1"
#245
0"
#250
b1001101000 %
b1001101000 *
b111010001 $
b111010001 )
b1100110000 '
b101011111 !
b101011111 &
b101011111 (
1"
#255
0"
#260
b1100110000 %
b1100110000 *
b1001101000 $
b1001101000 )
b10000111001 '
b111010001 !
b111010001 &
b111010001 (
1"
#265
0"
#270
b10000111001 %
b10000111001 *
b1100110000 $
b1100110000 )
b10110011000 '
b1001101000 !
b1001101000 &
b1001101000 (
1"
#275
0"
#280
b10110011000 %
b10110011000 *
b10000111001 $
b10000111001 )
b11101101001 '
b1100110000 !
b1100110000 &
b1100110000 (
1"
#285
0"
#290
b11101101001 %
b11101101001 *
b10110011000 $
b10110011000 )
b100111010001 '
b10000111001 !
b10000111001 &
b10000111001 (
1"
#295
0"
#300
b100111010001 %
b100111010001 *
b11101101001 $
b11101101001 )
b110100000001 '
b10110011000 !
b10110011000 &
b10110011000 (
1"
#305
0"
#310
b110100000001 %
b110100000001 *
b100111010001 $
b100111010001 )
b1000100111010 '
b11101101001 !
b11101101001 &
b11101101001 (
1"
#315
0"
#320
b1000100111010 %
b1000100111010 *
b110100000001 $
b110100000001 )
b1011011010010 '
b100111010001 !
b100111010001 &
b100111010001 (
1"
#325
0"
#330
b1011011010010 %
b1011011010010 *
b1000100111010 $
b1000100111010 )
b1111000111011 '
b110100000001 !
b110100000001 &
b110100000001 (
1"
#335
0"
#340
b1111000111011 %
b1111000111011 *
b1011011010010 $
b1011011010010 )
b10100000001100 '
b1000100111010 !
b1000100111010 &
b1000100111010 (
1"
#345
0"
#350
b10100000001100 %
b10100000001100 *
b1111000111011 $
b1111000111011 )
b11010100001101 '
b1011011010010 !
b1011011010010 &
b1011011010010 (
1"
#355
0"
#360
b11010100001101 %
b11010100001101 *
b10100000001100 $
b10100000001100 )
b100011001000111 '
b1111000111011 !
b1111000111011 &
b1111000111011 (
1"
#365
0"
#370
b100011001000111 %
b100011001000111 *
b11010100001101 $
b11010100001101 )
b101110100011001 '
b10100000001100 !
b10100000001100 &
b10100000001100 (
1"
#375
0"
#380
b101110100011001 %
b101110100011001 *
b100011001000111 $
b100011001000111 )
b111101101010100 '
b11010100001101 !
b11010100001101 &
b11010100001101 (
1"
#385
0"
#390
b111101101010100 %
b111101101010100 *
b101110100011001 $
b101110100011001 )
b1010001101100000 '
b100011001000111 !
b100011001000111 &
b100011001000111 (
1"
#395
0"
#400
b1010001101100000 %
b1010001101100000 *
b111101101010100 $
b111101101010100 )
b1101100001101101 '
b101110100011001 !
b101110100011001 &
b101110100011001 (
1"
#405
0"
#410
b1101100001101101 %
b1101100001101101 *
b1010001101100000 $
b1010001101100000 )
b10001111010110100 '
b111101101010100 !
b111101101010100 &
b111101101010100 (
1"
#415
0"
#420
b10001111010110100 %
b10001111010110100 *
b1101100001101101 $
b1101100001101101 )
b10111101111001101 '
b1010001101100000 !
b1010001101100000 &
b1010001101100000 (
1"
#425
0"
#430
b10111101111001101 %
b10111101111001101 *
b10001111010110100 $
b10001111010110100 )
b11111011100100001 '
b1101100001101101 !
b1101100001101101 &
b1101100001101101 (
1"
#435
0"
#440
b11111011100100001 %
b11111011100100001 *
b10111101111001101 $
b10111101111001101 )
b101001101010000001 '
b10001111010110100 !
b10001111010110100 &
b10001111010110100 (
1"
#445
0"
#450
b101001101010000001 %
b101001101010000001 *
b11111011100100001 $
b11111011100100001 )
b110111001011101110 '
b10111101111001101 !
b10111101111001101 &
b10111101111001101 (
1"
#455
0"
#460
b110111001011101110 %
b110111001011101110 *
b101001101010000001 $
b101001101010000001 )
b1001001000110100010 '
b11111011100100001 !
b11111011100100001 &
b11111011100100001 (
1"
#465
0"
#470
b1001001000110100010 %
b1001001000110100010 *
b110111001011101110 $
b110111001011101110 )
b1100000110101101111 '
b101001101010000001 !
b101001101010000001 &
b101001101010000001 (
1"
#475
0"
#480
b1100000110101101111 %
b1100000110101101111 *
b1001001000110100010 $
b1001001000110100010 )
b10000000010010010000 '
b110111001011101110 !
b110111001011101110 &
b110111001011101110 (
1"
#485
0"
#490
b10000000010010010000 %
b10000000010010010000 *
b1100000110101101111 $
b1100000110101101111 )
b10101001111100010001 '
b1001001000110100010 !
b1001001000110100010 &
b1001001000110100010 (
1"
#495
0"
#500
b10101001111100010001 %
b10101001111100010001 *
b10000000010010010000 $
b10000000010010010000 )
b11100001000111111111 '
b1100000110101101111 !
b1100000110101101111 &
b1100000110101101111 (
1"
#505
0"
#510
b11100001000111111111 %
b11100001000111111111 *
b10101001111100010001 $
b10101001111100010001 )
b100101010001110100001 '
b10000000010010010000 !
b10000000010010010000 &
b10000000010010010000 (
1"
#515
0"
#520
b100101010001110100001 %
b100101010001110100001 *
b11100001000111111111 $
b11100001000111111111 )
b110001011000100010000 '
b10101001111100010001 !
b10101001111100010001 &
b10101001111100010001 (
1"
#525
0"
#530
b110001011000100010000 %
b110001011000100010000 *
b100101010001110100001 $
b100101010001110100001 )
b1000001011010110100000 '
b11100001000111111111 !
b11100001000111111111 &
b11100001000111111111 (
1"
#535
0"
#540
b1000001011010110100000 %
b1000001011010110100000 *
b110001011000100010000 $
b110001011000100010000 )
b1010110101010010110001 '
b100101010001110100001 !
b100101010001110100001 &
b100101010001110100001 (
1"
#545
0"
#550
b1010110101010010110001 %
b1010110101010010110001 *
b1000001011010110100000 $
b1000001011010110100000 )
b1110010110011010110000 '
b110001011000100010000 !
b110001011000100010000 &
b110001011000100010000 (
1"
#555
0"
#560
b1110010110011010110000 %
b1110010110011010110000 *
b1010110101010010110001 $
b1010110101010010110001 )
b10011000000101001010001 '
b1000001011010110100000 !
b1000001011010110100000 &
b1000001011010110100000 (
1"
#565
0"
#570
b10011000000101001010001 %
b10011000000101001010001 *
b1110010110011010110000 $
b1110010110011010110000 )
b11001001011101101100001 '
b1010110101010010110001 !
b1010110101010010110001 &
b1010110101010010110001 (
1"
#575
0"
#580
b11001001011101101100001 %
b11001001011101101100001 *
b10011000000101001010001 $
b10011000000101001010001 )
b100001010111000100000001 '
b1110010110011010110000 !
b1110010110011010110000 &
b1110010110011010110000 (
1"
#585
0"
#590
b100001010111000100000001 %
b100001010111000100000001 *
b11001001011101101100001 $
b11001001011101101100001 )
b101100001100010110110010 '
b10011000000101001010001 !
b10011000000101001010001 &
b10011000000101001010001 (
1"
#595
0"
#600
b101100001100010110110010 %
b101100001100010110110010 *
b100001010111000100000001 $
b100001010111000100000001 )
b111010100010110001100010 '
b11001001011101101100001 !
b11001001011101101100001 &
b11001001011101101100001 (
1"
#605
0"
#610
b111010100010110001100010 %
b111010100010110001100010 *
b101100001100010110110010 $
b101100001100010110110010 )
b1001101100011011010110011 '
b100001010111000100000001 !
b100001010111000100000001 &
b100001010111000100000001 (
1"
#615
0"
#620
b1001101100011011010110011 %
b1001101100011011010110011 *
b111010100010110001100010 $
b111010100010110001100010 )
b1100110101111001000010100 '
b101100001100010110110010 !
b101100001100010110110010 &
b101100001100010110110010 (
1"
#625
0"
#630
b1100110101111001000010100 %
b1100110101111001000010100 *
b1001101100011011010110011 $
b1001101100011011010110011 )
b10001000000110001100010101 '
b111010100010110001100010 !
b111010100010110001100010 &
b111010100010110001100010 (
1"
