fibonacci_sequence_generator/fibonacci.sv
module fibonacci (
  input   logic        clk,
  input   logic        reset,

  output  logic [31:0] seq_o
);

  // Write your logic here...
  logic [31:0]  d1_in, d0_in;
  logic [31:0]  d1_out, d0_out;

assign d1_in = d1_out + d0_out;
assign d0_in = d1_out;

  always_ff @(posedge clk or posedge reset) begin
    if(reset) begin
      d0_out <= 32'd0;
      d1_out <= 32'd1;
    end
    else begin
      d0_out <= d0_in;
      d1_out <= d1_in;
    end
    
  end
  assign seq_o = d0_out;
endmodule

fibonacci_sequence_generator/tb_fibonacci.sv
module tb_fibonacci ();

  logic clk;
  logic reset;
  logic [31:0] seq_o;

  // Instantiate the Fibonacci module
  fibonacci uut (
    .clk(clk),
    .reset(reset),
    .seq_o(seq_o)
  );
  
  initial begin
    $dumpfile("fibonacci.vcd"); // Specify the VCD file for waveform output
    $dumpvars(0, tb_fibonacci); // Dump all variables in the testbench
  end


  // Clock generation
  initial begin
    clk = 0;
    forever #5 clk = ~clk; // Toggle clock every 5 time units
  end

  // Testbench stimulus
  initial begin
    reset = 1; // Assert reset
    #15;
    reset = 0; // Deassert reset

    // Wait for a few clock cycles to observe the output
    #600;

    $finish; // End simulation
  end

  endmodule

fibonacci_sequence_generator/fibonacci.vcd
$date
	Thu Jul 24 04:07:53 2025
$end
$version
	Icarus Verilog
$end
$timescale
	1s
$end
$scope module tb_fibonacci $end
$var wire 32 ! seq_o [31:0] $end
$var reg 1 " clk $end
$var reg 1 # reset $end
$scope module uut $end
$var wire 1 " clk $end
$var wire 32 $ d0_in [31:0] $end
$var wire 1 # reset $end
$var wire 32 % seq_o [31:0] $end
$var wire 32 & d1_in [31:0] $end
$var reg 32 ' d0_out [31:0] $end
$var reg 32 ( d1_out [31:0] $end
$upscope $end
$upscope $end
$enddefinitions $end
$comment Show the parameter values. $end
$dumpall
$end
#0
$dumpvars
b1 (
b0 '
b1 &
b0 %
b1 $
1#
0"
b0 !
$end
#5
1"
#10
0"
#15
b10 &
b1 !
b1 %
b1 '
1"
0#
#20
0"
#25
b11 &
b10 $
b10 (
1"
#30
0"
#35
b11 $
b11 (
b101 &
b10 !
b10 %
b10 '
1"
#40
0"
#45
b101 $
b101 (
b1000 &
b11 !
b11 %
b11 '
1"
#50
0"
#55
b1000 $
b1000 (
b1101 &
b101 !
b101 %
b101 '
1"
#60
0"
#65
b1101 $
b1101 (
b10101 &
b1000 !
b1000 %
b1000 '
1"
#70
0"
#75
b10101 $
b10101 (
b100010 &
b1101 !
b1101 %
b1101 '
1"
#80
0"
#85
b100010 $
b100010 (
b110111 &
b10101 !
b10101 %
b10101 '
1"
#90
0"
#95
b110111 $
b110111 (
b1011001 &
b100010 !
b100010 %
b100010 '
1"
#100
0"
#105
b1011001 $
b1011001 (
b10010000 &
b110111 !
b110111 %
b110111 '
1"
#110
0"
#115
b10010000 $
b10010000 (
b11101001 &
b1011001 !
b1011001 %
b1011001 '
1"
#120
0"
#125
b11101001 $
b11101001 (
b101111001 &
b10010000 !
b10010000 %
b10010000 '
1"
#130
0"
#135
b101111001 $
b101111001 (
b1001100010 &
b11101001 !
b11101001 %
b11101001 '
1"
#140
0"
#145
b1001100010 $
b1001100010 (
b1111011011 &
b101111001 !
b101111001 %
b101111001 '
1"
#150
0"
#155
b1111011011 $
b1111011011 (
b11000111101 &
b1001100010 !
b1001100010 %
b1001100010 '
1"
#160
0"
#165
b11000111101 $
b11000111101 (
b101000011000 &
b1111011011 !
b1111011011 %
b1111011011 '
1"
#170
0"
#175
b101000011000 $
b101000011000 (
b1000001010101 &
b11000111101 !
b11000111101 %
b11000111101 '
1"
#180
0"
#185
b1000001010101 $
b1000001010101 (
b1101001101101 &
b101000011000 !
b101000011000 %
b101000011000 '
1"
#190
0"
#195
b1101001101101 $
b1101001101101 (
b10101011000010 &
b1000001010101 !
b1000001010101 %
b1000001010101 '
1"
#200
0"
#205
b10101011000010 $
b10101011000010 (
b100010100101111 &
b1101001101101 !
b1101001101101 %
b1101001101101 '
1"
#210
0"
#215
b100010100101111 $
b100010100101111 (
b110111111110001 &
b10101011000010 !
b10101011000010 %
b10101011000010 '
1"
#220
0"
#225
b110111111110001 $
b110111111110001 (
b1011010100100000 &
b100010100101111 !
b100010100101111 %
b100010100101111 '
1"
#230
0"
#235
b1011010100100000 $
b1011010100100000 (
b10010010100010001 &
b110111111110001 !
b110111111110001 %
b110111111110001 '
1"
#240
0"
#245
b10010010100010001 $
b10010010100010001 (
b11101101000110001 &
b1011010100100000 !
b1011010100100000 %
b1011010100100000 '
1"
#250
0"
#255
b11101101000110001 $
b11101101000110001 (
b101111111101000010 &
b10010010100010001 !
b10010010100010001 %
b10010010100010001 '
1"
#260
0"
#265
b101111111101000010 $
b101111111101000010 (
b1001101100101110011 &
b11101101000110001 !
b11101101000110001 %
b11101101000110001 '
1"
#270
0"
#275
b1001101100101110011 $
b1001101100101110011 (
b1111101100010110101 &
b101111111101000010 !
b101111111101000010 %
b101111111101000010 '
1"
#280
0"
#285
b1111101100010110101 $
b1111101100010110101 (
b11001011001000101000 &
b1001101100101110011 !
b1001101100101110011 %
b1001101100101110011 '
1"
#290
0"
#295
b11001011001000101000 $
b11001011001000101000 (
b101001000101011011101 &
b1111101100010110101 !
b1111101100010110101 %
b1111101100010110101 '
1"
#300
0"
#305
b101001000101011011101 $
b101001000101011011101 (
b1000010011110100000101 &
b11001011001000101000 !
b11001011001000101000 %
b11001011001000101000 '
1"
#310
0"
#315
b1000010011110100000101 $
b1000010011110100000101 (
b1101011100011111100010 &
b101001000101011011101 !
b101001000101011011101 %
b101001000101011011101 '
1"
#320
0"
#325
b1101011100011111100010 $
b1101011100011111100010 (
b10101110000010011100111 &
b1000010011110100000101 !
b1000010011110100000101 %
b1000010011110100000101 '
1"
#330
0"
#335
b10101110000010011100111 $
b10101110000010011100111 (
b100011001100110011001001 &
b1101011100011111100010 !
b1101011100011111100010 %
b1101011100011111100010 '
1"
#340
0"
#345
b100011001100110011001001 $
b100011001100110011001001 (
b111000111101000110110000 &
b10101110000010011100111 !
b10101110000010011100111 %
b10101110000010011100111 '
1"
#350
0"
#355
b111000111101000110110000 $
b111000111101000110110000 (
b1011100001001111001111001 &
b100011001100110011001001 !
b100011001100110011001001 %
b100011001100110011001001 '
1"
#360
0"
#365
b1011100001001111001111001 $
b1011100001001111001111001 (
b10010101000111000000101001 &
b111000111101000110110000 !
b111000111101000110110000 %
b111000111101000110110000 '
1"
#370
0"
#375
b10010101000111000000101001 $
b10010101000111000000101001 (
b11110001010000111010100010 &
b1011100001001111001111001 !
b1011100001001111001111001 %
b1011100001001111001111001 '
1"
#380
0"
#385
b11110001010000111010100010 $
b11110001010000111010100010 (
b110000110010111111011001011 &
b10010101000111000000101001 !
b10010101000111000000101001 %
b10010101000111000000101001 '
1"
#390
0"
#395
b110000110010111111011001011 $
b110000110010111111011001011 (
b1001110111101000110101101101 &
b11110001010000111010100010 !
b11110001010000111010100010 %
b11110001010000111010100010 '
1"
#400
0"
#405
b1001110111101000110101101101 $
b1001110111101000110101101101 (
b1111111110000000110000111000 &
b110000110010111111011001011 !
b110000110010111111011001011 %
b110000110010111111011001011 '
1"
#410
0"
#415
b1111111110000000110000111000 $
b1111111110000000110000111000 (
b11001110101101001100110100101 &
b1001110111101000110101101101 !
b1001110111101000110101101101 %
b1001110111101000110101101101 '
1"
#420
0"
#425
b11001110101101001100110100101 $
b11001110101101001100110100101 (
b101001110011101010010111011101 &
b1111111110000000110000111000 !
b1111111110000000110000111000 %
b1111111110000000110000111000 '
1"
#430
0"
#435
b101001110011101010010111011101 $
b101001110011101010010111011101 (
b1000011101001010011111110000010 &
b11001110101101001100110100101 !
b11001110101101001100110100101 %
b11001110101101001100110100101 '
1"
#440
0"
#445
b1000011101001010011111110000010 $
b1000011101001010011111110000010 (
b1101101011100111110010101011111 &
b101001110011101010010111011101 !
b101001110011101010010111011101 %
b101001110011101010010111011101 '
1"
#450
0"
#455
b1101101011100111110010101011111 $
b1101101011100111110010101011111 (
b10110001000110010010010011100001 &
b1000011101001010011111110000010 !
b1000011101001010011111110000010 %
b1000011101001010011111110000010 '
1"
#460
0"
#465
b10110001000110010010010011100001 $
b10110001000110010010010011100001 (
b11110100011010000101001000000 &
b1101101011100111110010101011111 !
b1101101011100111110010101011111 %
b1101101011100111110010101011111 '
1"
#470
0"
#475
b11110100011010000101001000000 $
b11110100011010000101001000000 (
b11001111101001100010111100100001 &
b10110001000110010010010011100001 !
b10110001000110010010010011100001 %
b10110001000110010010010011100001 '
1"
#480
0"
#485
b11001111101001100010111100100001 $
b11001111101001100010111100100001 (
b11101110001100110011100101100001 &
b11110100011010000101001000000 !
b11110100011010000101001000000 %
b11110100011010000101001000000 '
1"
#490
0"
#495
b11101110001100110011100101100001 $
b11101110001100110011100101100001 (
b10111101110110010110100010000010 &
b11001111101001100010111100100001 !
b11001111101001100010111100100001 %
b11001111101001100010111100100001 '
1"
#500
0"
#505
b10111101110110010110100010000010 $
b10111101110110010110100010000010 (
b10101100000011001010000111100011 &
b11101110001100110011100101100001 !
b11101110001100110011100101100001 %
b11101110001100110011100101100001 '
1"
#510
0"
#515
b10101100000011001010000111100011 $
b10101100000011001010000111100011 (
b1101001111001100000101001100101 &
b10111101110110010110100010000010 !
b10111101110110010110100010000010 %
b10111101110110010110100010000010 '
1"
#520
0"
#525
b1101001111001100000101001100101 $
b1101001111001100000101001100101 (
b10101111100101010110001001000 &
b10101100000011001010000111100011 !
b10101100000011001010000111100011 %
b10101100000011001010000111100011 '
1"
#530
0"
#535
b10101111100101010110001001000 $
b10101111100101010110001001000 (
b1111111110110001011011010101101 &
b1101001111001100000101001100101 !
b1101001111001100000101001100101 %
b1101001111001100000101001100101 '
1"
#540
0"
#545
b1111111110110001011011010101101 $
b1111111110110001011011010101101 (
b10010101110010110110001011110101 &
b10101111100101010110001001000 !
b10101111100101010110001001000 %
b10101111100101010110001001000 '
1"
#550
0"
#555
b10010101110010110110001011110101 $
b10010101110010110110001011110101 (
b10101101001000001100110100010 &
b1111111110110001011011010101101 !
b1111111110110001011011010101101 %
b1111111110110001011011010101101 '
1"
#560
0"
#565
b10101101001000001100110100010 $
b10101101001000001100110100010 (
b10101011011011110111110010010111 &
b10010101110010110110001011110101 !
b10010101110010110110001011110101 %
b10010101110010110110001011110101 '
1"
#570
0"
#575
b10101011011011110111110010010111 $
b10101011011011110111110010010111 (
b11000001000100111001011000111001 &
b10101101001000001100110100010 !
b10101101001000001100110100010 %
b10101101001000001100110100010 '
1"
#580
0"
#585
b11000001000100111001011000111001 $
b11000001000100111001011000111001 (
b1101100100000110001001011010000 &
b10101011011011110111110010010111 !
b10101011011011110111110010010111 %
b10101011011011110111110010010111 '
1"
#590
0"
#595
b1101100100000110001001011010000 $
b1101100100000110001001011010000 (
b101101100101101010100100001001 &
b11000001000100111001011000111001 !
b11000001000100111001011000111001 %
b11000001000100111001011000111001 '
1"
#600
0"
#605
b101101100101101010100100001001 $
b101101100101101010100100001001 (
b10011010000110011011101111011001 &
b1101100100000110001001011010000 !
b1101100100000110001001011010000 %
b1101100100000110001001011010000 '
1"
#610
0"
#615
b10011010000110011011101111011001 $
b10011010000110011011101111011001 (
b11000111101100000110010011100010 &
b101101100101101010100100001001 !
b101101100101101010100100001001 %
b101101100101101010100100001001 '
1"
