config_timer.sv
module config_timer #(
    parameter CLOCK_TIME = 30
)
(
input logic clk, rst_n, input_trigger, emergency,
output logic signal_change
);
logic [$clog2(CLOCK_TIME):0] counter;
logic input_trigger_pulse, inp_trig_reg;

always_ff@(posedge clk) begin
    if(~rst_n)
        inp_trig_reg <= 1'b0;
    else 
        inp_trig_reg <= input_trigger;
end

assign input_trigger_pulse = input_trigger & ~inp_trig_reg;



always_ff @(posedge clk) begin
    if(~rst_n) begin
        counter <= '0;
    end
    else if (counter == CLOCK_TIME-1 | emergency) begin
        counter <= '0;
    end
    else begin
        counter <= (input_trigger_pulse || (counter > 0)) ? (counter + 1) : counter;
    end
end

assign signal_change = counter == (CLOCK_TIME-1);
endmodule

traffic_controller/config_timer_tb.sv
`timescale 1ns/1ns
`include "config_timer.sv"
module config_timer_tb;
reg clk, rst_n;
wire signal_change;
parameter CLK_PERIOD = 10;

config_timer config_timer_inst(.*);

//clock generation
always #((CLK_PERIOD/2))
clk = ~clk;

initial begin
    $dumpfile("config_timer_wf.vcd");
    $dumpvars(0, config_timer_tb);
    clk <= 1;
    rst_n <= 1'b1;
    #10;
    rst_n <= 1'b0; #10;
    rst_n <= 1'b1; #10;
    #270;
    rst_n <= 1'b0;
    #280;
    rst_n <= 1'b1;
    #1200;
    rst_n <= 1'b0;
    #1210;
    rst_n <= 1'b1;
    #2000;
    $finish;     
end
endmodule

traffic_controller/config_timer_wf.vcd
$date
	Tue Jan 21 00:05:57 2025
$end
$version
	Icarus Verilog
$end
$timescale
	1ns
$end
$scope module config_timer_tb $end
$var wire 1 ! signal_change $end
$var parameter 32 " CLK_PERIOD $end
$var reg 1 # clk $end
$var reg 1 $ rst_n $end
$scope module config_timer_inst $end
$var wire 1 # clk $end
$var wire 1 $ rst_n $end
$var wire 1 ! signal_change $end
$var parameter 32 % CLOCK_TIME $end
$var reg 6 & counter [5:0] $end
$upscope $end
$upscope $end
$enddefinitions $end
$comment Show the parameter values. $end
$dumpall
b11110 %
b1010 "
$end
#0
$dumpvars
bx &
1$
1#
x!
$end
#5
0#
#10
0$
1#
#15
0#
#20
0!
b0 &
1$
1#
#25
0#
#30
b1 &
1#
#35
0#
#40
b10 &
1#
#45
0#
#50
b11 &
1#
#55
0#
#60
b100 &
1#
#65
0#
#70
b101 &
1#
#75
0#
#80
b110 &
1#
#85
0#
#90
b111 &
1#
#95
0#
#100
b1000 &
1#
#105
0#
#110
b1001 &
1#
#115
0#
#120
b1010 &
1#
#125
0#
#130
b1011 &
1#
#135
0#
#140
b1100 &
1#
#145
0#
#150
b1101 &
1#
#155
0#
#160
b1110 &
1#
#165
0#
#170
b1111 &
1#
#175
0#
#180
b10000 &
1#
#185
0#
#190
b10001 &
1#
#195
0#
#200
b10010 &
1#
#205
0#
#210
b10011 &
1#
#215
0#
#220
b10100 &
1#
#225
0#
#230
b10101 &
1#
#235
0#
#240
b10110 &
1#
#245
0#
#250
b10111 &
1#
#255
0#
#260
b11000 &
1#
#265
0#
#270
b11001 &
1#
#275
0#
#280
b11010 &
1#
#285
0#
#290
b11011 &
1#
#295
0#
#300
b11100 &
0$
1#
#305
0#
#310
b0 &
1#
